LICENSE.md
README.md
setup.py
CQE/CQE.py
CQE/NumberNormalizer.py
CQE/__init__.py
CQE/classes.py
CQE/number_lookup.py
CQE/rules.py
CQE/unit.json
CQE/unit_conversion.py
CQE/unit_models.zip
CQE.egg-info/PKG-INFO
CQE.egg-info/SOURCES.txt
CQE.egg-info/dependency_links.txt
CQE.egg-info/requires.txt
CQE.egg-info/top_level.txt
CQE/unit_classifier/__init__.py
CQE/unit_classifier/sample_usage.py
CQE/unit_classifier/train_classifier_bert.py
CQE/unit_classifier/unit_disambiguator.py