Metadata-Version: 2.1
Name: CQE
Version: 2.0.0
Summary: quantity extractor
Home-page: https://github.com/vivkaz/CQE
Author: satyaalmasian and vivian kazakova
Author-email: satya.almasian@gmail.com
License-File: LICENSE.md
